{
  "updated_at": "2026-03-16T18:43:25.604083+00:00",
  "count": 12,
  "events": [
    {
      "name": "Belgian Open 2026",
      "url": "https://worldtkd.simplycompete.com/eventDetails/11f0eee4-b227-4eda-9f64-027be1645a55/1",
      "date": "03/21/2026",
      "deadline": null,
      "location": "Lommel, Belgium",
      "country": "Belgium",
      "source": "World Taekwondo (SimplyCompete)"
    },
    {
      "name": "(Poomsae) Turkiye Open 2026",
      "url": "https://worldtkd.simplycompete.com/eventDetails/11f0f92c-141a-9981-a1db-066b11207e5b/1",
      "date": "03/24/2026",
      "deadline": null,
      "location": "Antalya, Türkiye",
      "country": "Türkiye",
      "source": "World Taekwondo (SimplyCompete)"
    },
    {
      "name": "(Para Kyorugi) 2026 Turkiye Open",
      "url": "https://worldtkd.simplycompete.com/eventDetails/11f0f92d-bd2c-f52e-a1db-066b11207e5b/1",
      "date": "03/25/2026",
      "deadline": null,
      "location": "Antalya, Türkiye",
      "country": "Türkiye",
      "source": "World Taekwondo (SimplyCompete)"
    },
    {
      "name": "(Para Poomsae) Turkiye Open 2026",
      "url": "https://worldtkd.simplycompete.com/eventDetails/11f0f92e-cfd7-bfb6-a1db-066b11207e5b/1",
      "date": "03/25/2026",
      "deadline": null,
      "location": "Antalya, Türkiye",
      "country": "Türkiye",
      "source": "World Taekwondo (SimplyCompete)"
    },
    {
      "name": "2026 Oceania Taekwondo Championships",
      "url": "https://worldtkd.simplycompete.com/eventDetails/11f0f882-087e-09c3-abeb-02e00a1b3d49/1",
      "date": "03/28/2026",
      "deadline": null,
      "location": "Sydney, Australia",
      "country": "Australia",
      "source": "World Taekwondo (SimplyCompete)"
    },
    {
      "name": "(Team) 2026 Oceania Taekwondo Championships",
      "url": "https://worldtkd.simplycompete.com/eventDetails/11f0f883-d0ad-a324-abeb-02e00a1b3d49/1",
      "date": "03/28/2026",
      "deadline": null,
      "location": "Sydney, Australia",
      "country": "Australia",
      "source": "World Taekwondo (SimplyCompete)"
    },
    {
      "name": "(Kyorugi) Turkiye Open 2026",
      "url": "https://worldtkd.simplycompete.com/eventDetails/11f0f92a-6201-725f-a1db-066b11207e5b/1",
      "date": "03/26/2026",
      "deadline": null,
      "location": "Antalya, Türkiye",
      "country": "Türkiye",
      "source": "World Taekwondo (SimplyCompete)"
    },
    {
      "name": "2026 African Para Taekwondo Poomsae Championships",
      "url": "https://worldtkd.simplycompete.com/eventDetails/11f0fdc6-d50b-d683-a1db-066b11207e5b/1",
      "date": "04/01/2026",
      "deadline": null,
      "location": "RABAT, MOROCCO",
      "country": "RABAT, MOROCCO",
      "source": "World Taekwondo (SimplyCompete)"
    },
    {
      "name": "2026 African Para Taekwondo Championships",
      "url": "https://worldtkd.simplycompete.com/eventDetails/11f0fdc7-0a4d-b820-a1db-066b11207e5b/1",
      "date": "04/04/2026",
      "deadline": null,
      "location": "RABAT, MOROCCO",
      "country": "RABAT, MOROCCO",
      "source": "World Taekwondo (SimplyCompete)"
    },
    {
      "name": "(Kyorugi) Skopje Open Ramus 2026",
      "url": "https://worldtkd.simplycompete.com/eventDetails/11f0f87d-5977-f774-abeb-02e00a1b3d49/1",
      "date": "04/04/2026",
      "deadline": null,
      "location": "Skopje, North Macedonia",
      "country": "North Macedonia",
      "source": "World Taekwondo (SimplyCompete)"
    },
    {
      "name": "2026 African Championships",
      "url": "https://worldtkd.simplycompete.com/eventDetails/11f0fd43-c083-9438-a1db-066b11207e5b/1",
      "date": "04/01/2026",
      "deadline": null,
      "location": "RABAT, MOROCCO",
      "country": "RABAT, MOROCCO",
      "source": "World Taekwondo (SimplyCompete)"
    },
    {
      "name": "(Poomsae) Skopje Open Ramus 2026",
      "url": "https://worldtkd.simplycompete.com/eventDetails/11f10e8a-ef02-f48f-9c46-066b11207e5b/1",
      "date": "04/05/2026",
      "deadline": null,
      "location": "Skopje, North Macedonia",
      "country": "North Macedonia",
      "source": "World Taekwondo (SimplyCompete)"
    }
  ]
}